README.md
setup.py
PiecewiseBeta/PiecewiseBeta.py
PiecewiseBeta/__init__.py
PiecewiseBeta.egg-info/PKG-INFO
PiecewiseBeta.egg-info/SOURCES.txt
PiecewiseBeta.egg-info/dependency_links.txt
PiecewiseBeta.egg-info/requires.txt
PiecewiseBeta.egg-info/top_level.txt